{
    "aid": "01",
    "cardList": "075.422;075.423;075.424",
    "albumID": "075.422",
    "place": "दिल्ली",
    "troupe": "श्रीराम सेंटर रंगमंडल",
    "drama": "जाँच पड़ताल (हिन्दी) (हास्य नाटक)",
    "writer": "संजय सहाय",
    "director": "सुरेश शर्मा",
    "asstdirector": "राजेश तिवारी",
    "costume": "विनीता टण्डन, राजेन्द्र नेगी",
    "make-up": "अनवर उल्लाह, राम कुमार",
    "stage": "सत्यव्रत राऊत",
    "light": "रवीन्द्र मिश्रा",
    "music": "मोहन उप्रेती",
    "artist": "मयार (राजेश शर्मा), राजेश तिवारी (कुमार), मीना वैभव, रचना जोशी (इमर्तीदेवी), विनीता टण्डन (बेबी), अनवर उल्लाह (स्कूल इंस्पैक्टर), राजेन्द्र नेगी (कोतवाल) (पोस्टमैन)",
    "venue": "श्रीराम सेंटर सभागार",
    "date": "16-19 जनवरि 1997"
}