{
    "aid": "01",
    "cardList": "077.113;077.114",
    "albumID": "077.113",
    "state": "महाराष्ट्र",
    "place": "मुम्बई",
    "troupe": "एकजुट",
    "drama": "इतिहास तुम्हें ले गया कहाँकन्हैया",
    "writer": "धर्मवीर भारती",
    "projection": "पुष्पा भारती व नादिरा ज़हीर बब्बर",
    "director": "नादिरा ज़हीर बब्बर",
    "choreography": "उमा डोगरा व सी. गोपालकृष्णन",
    "music": "आमोद भट्ट",
    "costume": "शैली सथ्यू, जूही बब्बर",
    "make-up": "अनिल मेकअप सर्विस",
    "sound": "कृष्ण (राज बब्बर)",
    "stage": "चहल-परेश",
    "light": "रवि मिश्रा",
    "artist": "कनुप्रिया (जूही बब्बर), धृतराष्ट्र (दर्पण मिश्रा) व अन्य"
}