{
    "aid": "01",
    "cardList": "077.081;077.082;077.083",
    "albumID": "077.081",
    "state": "महाराष्ट्र",
    "place": "बम्बई",
    "troupe": "आविष्कार",
    "drama": "पोस्टर",
    "writer": "शंकर शेष",
    "director": "जयदेव हट्टंगडी",
    "asstdirection": "अजित भगत",
    "music": "शॉक नील",
    "costume": "देवीदास पित्तले (Pitle)",
    "stage": "सीताराम कुंभार, सीताराम कदम व अन्य",
    "light": "प्रभाकर गोखले",
    "producer": "अरुण काकड़े",
    "artist": "चन्द्रशेखर कामरेकर, अशांक कुलकर्णी (सूत्रधार), प्रभाकर कर्ले (पटेल), अविनाश स्मार्त (कल्लू), श्रीकांत दादरकर (गुरुजी), चन्द्रशेखर कामरेकर (स्वामी) व अन्य",
    "venue": "मंज़र थिएटर, प्रगति मैदान, दिल्ली",
    "date": "25-02-1985"
}