{
    "aid": "01",
    "cardList": "077.239;077.240",
    "albumID": "077.239",
    "state": "महाराष्ट्र",
    "place": "बम्बई",
    "troupe": "मोटले",
    "drama": "वेटिंग फॉर गोडो (अँग्रेजी)",
    "writer": "सैमुअल ब्रेख़्त",
    "director": "बैंजमिन गिलानी",
    "make-up": "जयराज पाटील",
    "stage": "जयराज पाटील",
    "light": "रत्ना पाठक शाह",
    "artist": "बैंजमिन गिलानी (एस्ट्रागन), नसीरुद्दीन शाह (ल्लादिमिर), करीम वकील (लक्की), आकाश खुराना (पोज्जो), विवान असद शाह (लड़का)",
    "venue": "श्रीराम सेन्टर सभागार, दिल्ली",
    "host": "नटरंग प्रतिष्ठान",
    "date": "5 नवम्बर 1998"
}